hokora/__init__.py
hokora-0.1.5.dist-info/licenses/COPYING
hokora-0.1.5.dist-info/METADATA
hokora-0.1.5.dist-info/WHEEL
hokora-0.1.5.dist-info/entry_points.txt
hokora-0.1.5.dist-info/top_level.txt
hokora-0.1.5.dist-info/RECORD
