Metadata-Version: 2.4
Name: hokora
Version: 0.1.5
Summary: A stand-alone renderer for Jinja2 templates
License-Expression: BSD-3-Clause
Project-URL: Homepage, https://gitlab.com/drmoose/hokora
Project-URL: Issues, https://gitlab.com/drmoose/hokora/-/issues
Project-URL: Repository, https://gitlab.com/drmoose/hokora.git
Requires-Python: >=3.10
License-File: COPYING
Requires-Dist: jinja2
Provides-Extra: check
Requires-Dist: ruff; extra == "check"
Requires-Dist: mypy; extra == "check"
Provides-Extra: toml
Requires-Dist: toml; extra == "toml"
Provides-Extra: yaml
Requires-Dist: PyYAML; extra == "yaml"
Provides-Extra: all
Requires-Dist: hokora[toml,yaml]; extra == "all"
Dynamic: license-file
